{
  "numero_de_permis": "A0001",
  "cycle": "2020-2022",
  "heures_transferees_du_cycle_precedent": 7,
  "activites": [
    {
      "description": "Cours sur la déontologie",
      "categorie": "cours",
      "heures": 9,
      "date": "21-02-2020"
    },
    {
      "description": "Séminaire sur l'architecture contemporaine",
      "categorie": "séminaire",
      "heures": 8,
      "date": "2021-01-07"
    },
    {
      "description": "Rédaction pour le magazine Architecture moderne",
      "categorie": "rédaction professionnelle",
      "heures": 6,
      "date": "2021-10-22"
    },
    {
      "description": "Participation à un groupe de discussion sur le partage des projets architecturaux de plus de 20 ans",
      "categorie": "groupe de discussion",
      "heures": 17,
      "date": "2021-04-01"
    },
    {
      "description": "Visite d'établissements architecturaux",
      "categorie": "voyage",
      "heures": 4,
      "date": "2021-02-02"
    }
  ]
}

